Toggl_API_Bill_Generator-1.0.0.data/scripts/toggl-bill-gen
Toggl_API_Bill_Generator-1.0.0.data/scripts/toggl-gen
toggl_api_bill_generator/__init__.py
toggl_api_bill_generator/main_constants.py
toggl_api_bill_generator/toggl_constants.py
Toggl_API_Bill_Generator-1.0.0.dist-info/LICENSE
Toggl_API_Bill_Generator-1.0.0.dist-info/METADATA
Toggl_API_Bill_Generator-1.0.0.dist-info/WHEEL
Toggl_API_Bill_Generator-1.0.0.dist-info/top_level.txt
Toggl_API_Bill_Generator-1.0.0.dist-info/RECORD
